lsp/__init__.py
lsp/client.cpython-313-darwin.so
lsp/client.py
lsp/client_manager.cpython-313-darwin.so
lsp/client_manager.py
lsp/constants.cpython-313-darwin.so
lsp/constants.py
lsp/managed_client.cpython-313-darwin.so
lsp/managed_client.py
lsp/protocol.cpython-313-darwin.so
lsp/protocol.py
lsp/timeouts.cpython-313-darwin.so
lsp/timeouts.py
lsp/operations/__init__.py
lsp/operations/base.cpython-313-darwin.so
lsp/operations/base.py
lsp/operations/definition.cpython-313-darwin.so
lsp/operations/definition.py
lsp/operations/document_symbols.cpython-313-darwin.so
lsp/operations/document_symbols.py
lsp/operations/hover.cpython-313-darwin.so
lsp/operations/hover.py
lsp/operations/references.cpython-313-darwin.so
lsp/operations/references.py
lsp/operations/symbol_position.cpython-313-darwin.so
lsp/operations/symbol_position.py
swiftlens_core-0.1.9.dist-info/licenses/LICENSE
swiftlens_core-0.1.9.dist-info/METADATA
swiftlens_core-0.1.9.dist-info/WHEEL
swiftlens_core-0.1.9.dist-info/top_level.txt
swiftlens_core-0.1.9.dist-info/RECORD
